train_test_plot/__init__.py
train_test_plot/train_test_plot.py
train_test_plot-1.2.7.dist-info/LICENSE
train_test_plot-1.2.7.dist-info/METADATA
train_test_plot-1.2.7.dist-info/WHEEL
train_test_plot-1.2.7.dist-info/top_level.txt
train_test_plot-1.2.7.dist-info/RECORD
